setup.py
n2txt/__init__.py
n2txt/main.py
noveldumper.egg-info/PKG-INFO
noveldumper.egg-info/SOURCES.txt
noveldumper.egg-info/dependency_links.txt
noveldumper.egg-info/entry_points.txt
noveldumper.egg-info/not-zip-safe
noveldumper.egg-info/requires.txt
noveldumper.egg-info/top_level.txt