Metadata-Version: 1.0
Name: noveldumper
Version: 0.0.3
Summary: Dump novel from site to txt file
Home-page: https://github.com/ipconfiger/noveldumper
Author: Alexander.Li
Author-email: superpowerlee@gmail.com
License: GNU Lesser General Public License v3.0
Platform: UNKNOWN
